_openmp_mutex/__init__.py
openmp_mutex-0.1.0.dist-info/METADATA
openmp_mutex-0.1.0.dist-info/WHEEL
openmp_mutex-0.1.0.dist-info/top_level.txt
openmp_mutex-0.1.0.dist-info/RECORD
